gui_stream/__init__.py
gui_stream/__main__.py
gui_stream/_version.py
gui_stream/controller_app.py
gui_stream/home_page.py
gui_stream/launch.py
gui_stream/page_convert_pdf.py
gui_stream/page_images.py
gui_stream/page_maps.py
gui_stream/page_ocr.py
gui_stream/page_sheets.py
gui_stream/app_ui/__init__.py
gui_stream/app_ui/run_app.py
gui_stream/app_ui/core/__init__.py
gui_stream/app_ui/core/menu_bar.py
gui_stream/app_ui/core/observer.py
gui_stream/app_ui/core/page.py
gui_stream/app_ui/core/progress.py
gui_stream/app_ui/core/select_files.py
gui_stream/app_ui/core/themes.py
gui_stream/app_ui/ui/__init__.py
gui_stream/app_ui/ui/ui_menu_bar.py
gui_stream/app_ui/ui/ui_pages.py
gui_stream/app_ui/ui/widgets.py
gui_stream/pymaps/__init__.py
gui_stream/pymaps/_read_sheets.py
gui_stream/pymaps/create_maps.py
gui_stream/pymaps/map_adapter.py
gui_stream/sheets/__init__.py
gui_stream/sheets/load.py
gui_stream/sheets/parse.py
gui_stream/sheets/save.py
gui_stream/sheets/utm_convert.py
gui_stream/sheets/models/__init__.py
gui_stream/sheets/models/m_progress.py
gui_stream/sheets/utils/__init__.py
gui_stream-2.3.3.dist-info/METADATA
gui_stream-2.3.3.dist-info/WHEEL
gui_stream-2.3.3.dist-info/top_level.txt
gui_stream-2.3.3.dist-info/RECORD
