Metadata-Version: 2.4
Name: gui_stream
Version: 2.3.3
Summary: Interface gráfica para conversão de documentos e extraão de texto com ocr.
Author: Bruno Chaves
Requires-Python: >=3.11
Requires-Dist: PyMuPDF
Requires-Dist: reportlab
Requires-Dist: openpyxl
Requires-Dist: pandas
Requires-Dist: opencv-python
Requires-Dist: gmplot
Requires-Dist: odfpy
Requires-Dist: soup_files>=1.3
Requires-Dist: convert_stream>=2.4.4
Requires-Dist: ocr_stream>=2.4.2
